<?xml version="1.0" encoding="utf-8"?>
<LanguageData>

  <!-- Titles -> Ranks / Honor -> Votes -->
  <LetterLabelLostRoyalTitle>Rang {PAWN_labelShort} perdu : {PAWN_labelShort}</LetterLabelLostRoyalTitle>
  <LetterLabelGainedRoyalTitle>Rang {PAWN_labelShort} obtenu : {PAWN_labelShort}</LetterLabelGainedRoyalTitle>

  <LetterGainedRoyalTitle>{FACTION_name} a reçu le rang de {FACTION_name} de {FACTION_name} !</LetterGainedRoyalTitle>
  <LetterLostRoyalTitle>{FACTION_name} ne détient plus le rang de {FACTION_name} avec {FACTION_name}.</LetterLostRoyalTitle>
  <LetterLabelRewardsForNewTitle>Récompenses de classement</LetterLabelRewardsForNewTitle>
  <LetterRewardsForNewTitle>Pour honorer l'avancement de {PAWN_objective} au rang de {PAWN_objective}, {PAWN_objective} a envoyé à {PAWN_objective} la ou les récompenses suivantes :</LetterRewardsForNewTitle>

  <LetterPartBestowingExtraHonor>{3} a reçu des votes {3} en signe de respect de la part de {3}, pour avoir rassemblé des spectateurs {3}.</LetterPartBestowingExtraHonor>
  <LetterPartNoExtraHonor>{PAWN_labelShort} n'a ​​reçu aucun vote supplémentaire car il n'y avait pas beaucoup de spectateurs.</LetterPartNoExtraHonor>
  <LetterTextHonorAward_BanditCamp>À qui faut-il créditer les votes {0} pour avoir vaincu le camp des bandits ?</LetterTextHonorAward_BanditCamp>

  <!-- Shuttle/Vertibird -->
  <LetterLabelShuttleCrashed>Vertibird s'est écrasé</LetterLabelShuttleCrashed>
  <LetterTextShuttleCrashed>Un Vertibird s'est écrasé à proximité</LetterTextShuttleCrashed>

  <!-- Bestowing ceremony texts updated to use rank terminology -->
  <LetterLabelBestowingCeremonyTitleUpdated>Le rang de {TARGET_definite} a changé</LetterLabelBestowingCeremonyTitleUpdated>
  <LetterTextBestowingCeremonyTitleUpdated>{TARGET_definite} a acquis un nouveau rang depuis la programmation de la cérémonie de remise. Afin que l'attribution corresponde au nouveau rang, une autre cérémonie sera programmée prochainement.

La nouvelle cérémonie d'attribution comprendra les récompenses cryptides pour tous les rangs qui n'ont pas encore été attribués.</LetterTextBestowingCeremonyTitleUpdated>

  <!-- Tribute collector -> Enclave representative -->
  <LetterLabelTributeCollectorArrival>Arrivée du représentant de l’enclave</LetterLabelTributeCollectorArrival>
  <LetterTributeCollectorArrival>Un représentant de l'enclave de {FACTION_name} approche.\n\nIls accepteront tous les prisonniers et ressources que vous offrirez en hommage. Celui qui rendra l'hommage recevra {FACTION_name} pour son soutien à l'enclave.

Vous pouvez vous attendre à ce qu'un représentant de l'enclave arrive environ deux fois par an tant que vous n'êtes pas ennemi de {FACTION_name}.</LetterTributeCollectorArrival>

</LanguageData>
