<?xml version="1.0" encoding="utf-8"?>
<LanguageData>
<VF_MustSelectColorPalette>Doit avoir une palette sélectionnée pour enregistrer.</VF_MustSelectColorPalette>
  <VF_VehicleUnableToMove>{0_labelShort} ne peut pas bouger.</VF_VehicleUnableToMove>
  <VF_VehicleImmobileDeployed>{0_labelShort} est déployé et ne peut pas être déplacé.</VF_VehicleImmobileDeployed>
  <VF_HandlerNotEnoughRoom>Échec de l'ajout de {0} à {1}. Plus de place disponible.</VF_HandlerNotEnoughRoom>
  <VF_NotEnoughToOperate>Il a besoin de plus d’équipage pour fonctionner.</VF_NotEnoughToOperate>
  <VF_OutOfFuel>Impossible de rédiger. Le véhicule a besoin de plus de carburant.</VF_OutOfFuel>
  <VF_UpgradeInProgress>Impossible de drafter pendant la mise à niveau du véhicule.</VF_UpgradeInProgress>
  <VF_NotEnoughCrew>Pas assez de colons dans {0} pour faire fonctionner {1}.</VF_NotEnoughCrew>
  <VF_CannotFit>Pas assez d'espace.</VF_CannotFit>
  <VF_NoPathForVehicle>Impossible de cheminer ici.</VF_NoPathForVehicle>
  <VF_IncapableStatusForRole>{0} est incapable de remplir ce rôle.</VF_IncapableStatusForRole>
  <VF_InvalidName>Nom invalide pour le véhicule.</VF_InvalidName>
  <VF_OutOfFood>Pas de nourriture à {0} avec des pions à bord.</VF_OutOfFood>
  <VF_NoAmmoLoadedTurret>Aucune munition chargée.</VF_NoAmmoLoadedTurret>
  <VF_NoAmmoAvailable>Aucune munition disponible dans l'inventaire.</VF_NoAmmoAvailable>
  <VF_VehicleCaravanMentalBreakMovementRole>{0} n'est plus en mesure de jouer son rôle pour la caravane de véhicules.</VF_VehicleCaravanMentalBreakMovementRole>
  <VF_PawnBoardedFormingCaravan>{0} est monté à bord du {1} et est prêt à partir.</VF_PawnBoardedFormingCaravan>
  <VF_CantMoveDocked>Pas assez de pions pour mettre les voiles.</VF_CantMoveDocked>
  <VF_CantAssignVehicle>Pas assez de pions pour {0}.</VF_CantAssignVehicle>
  <VF_AssignFailure>Échec de l'attribution des sièges. {0}</VF_AssignFailure>
  <VF_PackingSpotNotFound>Le lieu d'emballage n'a pas été trouvé pour la caravane de véhicule. Il est recommandé de placer un point d'emballage de Misc.</VF_PackingSpotNotFound>
  <VF_ForceLeaveCaravan>Forcer à partir</VF_ForceLeaveCaravan>
  <VF_ForceLeaveCaravanDesc>Forcer la caravane du véhicule à quitter la carte. Ignorera le chargement des éléments qui ne sont pas actuellement à bord.</VF_ForceLeaveCaravanDesc>
  <VF_ForceLeaveConfirmation>L'équipage se prépare à partir.</VF_ForceLeaveConfirmation>
  <VF_CaravanTerminatedNoVehicles>Le processus de caravane a été interrompu. Il ne reste aucun véhicule.</VF_CaravanTerminatedNoVehicles>
  <VF_LandAndSeaRoutePlannerRestriction>Impossible de planifier un itinéraire pour les véhicules maritimes et terrestres. Les chemins ne seront pas enregistrés.</VF_LandAndSeaRoutePlannerRestriction>
  <VF_LeaveVehicleBehindCaravan>Êtes-vous sûr de vouloir laisser les véhicules derrière vous ? Véhicules abandonnés : {0}</VF_LeaveVehicleBehindCaravan>
  <VF_MustAssignEnoughToVehicle>Doit affecter suffisamment de colons au véhicule de l'homme.</VF_MustAssignEnoughToVehicle>
  <VF_AerialVehicleArrived>{0} est arrivé à destination.</VF_AerialVehicleArrived>
  <VF_AerialVehicleLeft>{0} a quitté la carte.</VF_AerialVehicleLeft>
  <VF_AerialVehicleLaunchNotValid>Impossible de lancer, les conditions ne sont pas adaptées.</VF_AerialVehicleLaunchNotValid>
  <VF_LaunchOutOfFuel>Impossible de lancer. À court de carburant.</VF_LaunchOutOfFuel>
  <VF_FlightPathMaxNodes>Le nombre maximum de nœuds pour la trajectoire de vol de {0} a été atteint.</VF_FlightPathMaxNodes>
  <VF_MustTargetLanding>Une destination d'atterrissage doit être choisie.</VF_MustTargetLanding>
</LanguageData>
