<?xml version="1.0" encoding="utf-8"?>
<LanguageData>
    <Pungaling.label>pungaling</Pungaling.label>
    <Pungaling.description>Una casta lenta e maldestra di treeminder specializzata nella produzione di pung. Insieme al suo albero Gauranlen, questa driade può generare frutti punga in modo continuativo. Tuttavia, è lento e inefficace sul lavoro o in combattimento.</Pungaling.description>
    <VDE_Stonedigger.description>Una casta di guardiani degli alberi estremamente accomodante specializzata nel trascinare pezzi di pietra. Assorbe i minerali dal terreno per indurire la sua pelle lasciando da parte i pezzi sovradimensionati.</VDE_Stonedigger.description>
    <VDE_Spitter.description>Una casta di guardiani degli alberi specializzata nella difesa del territorio in grado di lanciare proiettili corrosivi. Sebbene possa infliggere danni enormi, rimane vulnerabile nel corpo a corpo a causa delle sue fauci sovradimensionate.</VDE_Spitter.description>
    <VDE_Gaubricmaker.description>Una casta di guardiani degli alberi specializzata nella produzione di una pelle ispida simile al cuoio. Insieme al suo PadreAlbero, può essere tosato su base continuativa per ottenere un materiale morbido e isolante, sebbene sia lento e inefficace sul lavoro o in combattimento.</VDE_Gaubricmaker.description>
    <VDE_Nectarmaker.description>Una curiosa casta di guardiani degli alberi specializzata nella produzione di linfa rinvigorente. Insieme al suo Padrealbero può generare continuamente questo raccolto stimolante, ma è completamente indifeso e richiede un'attenta protezione.</VDE_Nectarmaker.description>
</LanguageData>
