<?xml version="1.0" encoding="utf-8"?>
<LanguageData>

  <!-- Titles -> Ranks / Honor -> Votes -->
  <LetterLabelLostRoyalTitle>{PAWN_labelShort}-rang verloren: {PAWN_labelShort}</LetterLabelLostRoyalTitle>
  <LetterLabelGainedRoyalTitle>{PAWN_labelShort}-rang behaald: {PAWN_labelShort}</LetterLabelGainedRoyalTitle>

  <LetterGainedRoyalTitle>{FACTION_name} ontving de rang van {FACTION_name} van {FACTION_name}!</LetterGainedRoyalTitle>
  <LetterLostRoyalTitle>{FACTION_name} heeft niet langer de rang van {FACTION_name} met {FACTION_name}.</LetterLostRoyalTitle>
  <LetterLabelRewardsForNewTitle>Rang beloningen</LetterLabelRewardsForNewTitle>
  <LetterRewardsForNewTitle>Om te eren dat {PAWN_objective} doorgroeit naar de rang van {PAWN_objective}, heeft {PAWN_objective} {PAWN_objective} de volgende beloning(en) gestuurd:</LetterRewardsForNewTitle>

  <LetterPartBestowingExtraHonor>{3} ontving {3}-stemmen als teken van respect van {3} voor het verzamelen van {3}-toeschouwers.</LetterPartBestowingExtraHonor>
  <LetterPartNoExtraHonor>{PAWN_labelShort} kreeg geen extra stemmen omdat er niet veel toeschouwers waren.</LetterPartNoExtraHonor>
  <LetterTextHonorAward_BanditCamp>Aan wie moeten de {0}-stemmen worden gecrediteerd voor het verslaan van het bandietenkamp?</LetterTextHonorAward_BanditCamp>

  <!-- Shuttle/Vertibird -->
  <LetterLabelShuttleCrashed>Vertibird is neergestort</LetterLabelShuttleCrashed>
  <LetterTextShuttleCrashed>In de buurt is een Vertibird neergestort</LetterTextShuttleCrashed>

  <!-- Bestowing ceremony texts updated to use rank terminology -->
  <LetterLabelBestowingCeremonyTitleUpdated>De rang van {TARGET_definite} is gewijzigd</LetterLabelBestowingCeremonyTitleUpdated>
  <LetterTextBestowingCeremonyTitleUpdated>{TARGET_definite} heeft een nieuwe rang gekregen sinds de schenkingsceremonie was gepland. Om het schenken in overeenstemming te brengen met de nieuwe rang, zal er binnenkort een nieuwe ceremonie worden gepland.

De nieuwe schenkingsceremonie omvat de cryptische inzichtbeloningen voor alle rangen die nog niet zijn toegekend.</LetterTextBestowingCeremonyTitleUpdated>

  <!-- Tribute collector -> Enclave representative -->
  <LetterLabelTributeCollectorArrival>Aankomst van de enclavevertegenwoordiger</LetterLabelTributeCollectorArrival>
  <LetterTributeCollectorArrival>Er nadert een enclavevertegenwoordiger van {FACTION_name}.\n\nZe accepteren alle gevangenen en middelen die je aanbiedt als eerbetoon. Degene die het eerbetoon overhandigt, ontvangt {FACTION_name} voor het steunen van de enclave.

Je kunt verwachten dat er ongeveer twee keer per jaar een enclavevertegenwoordiger arriveert, zolang je geen vijanden bent met {FACTION_name}.</LetterTributeCollectorArrival>

</LanguageData>
