<?xml version="1.0" encoding="utf-8"?>
<LanguageData>
  <!-- Mod options -->
  <!-- Bills -->

  <NocturnalAnimals.BodyClock>Relógio biológico</NocturnalAnimals.BodyClock>
  <NocturnalAnimals.BodyClock_Description>Determina quando o animal dorme e quando está acordado.\n\nAnimais diurnos dormem durante a noite e ficam acordados durante o dia, enquanto animais noturnos dormem durante o dia e ficam acordados durante a noite. Os animais crepusculares são ativos principalmente durante o anoitecer.</NocturnalAnimals.BodyClock_Description>
  <NocturnalAnimals.BodyClock_Diurnal>Diurno</NocturnalAnimals.BodyClock_Diurnal>
  <NocturnalAnimals.BodyClock_Nocturnal>Noturno</NocturnalAnimals.BodyClock_Nocturnal>
  <NocturnalAnimals.BodyClock_Crepuscular>Crepuscular</NocturnalAnimals.BodyClock_Crepuscular>
  <VEF_AsexualHatched>{0} se reproduziu assexuadamente.</VEF_AsexualHatched>
  <VEF_AsexualCloning>{0} se clonou.</VEF_AsexualCloning>
  <VEF_AsexualHatchedEgg>{0} esporulou.</VEF_AsexualHatchedEgg>
  <VEF_NotTameable>Esta criatura é indomável</VEF_NotTameable>
  <VEF_TimeToMetamorphosis>Hora da metamorfose: {0}</VEF_TimeToMetamorphosis>
  <VEF_WarningEggExplodes>Atenção, este ovo explode ao eclodir!</VEF_WarningEggExplodes>
  <VEF_TimeToDie>O animal expira em: {0}</VEF_TimeToDie>
  <VEF_DisableAnimal>Desativar {0}</VEF_DisableAnimal>
  <VEF_StomachContents>{0} criaturas engolidas inteiras.</VEF_StomachContents>
  <VEF_DigestionTime>Será consumido em {0}</VEF_DigestionTime>
  <VEF_TerrainsNeedsDiggable>O terreno precisa ser escavado para fazer isso</VEF_TerrainsNeedsDiggable>
  <VEF_WhileCaravaning>Durante a caravana, produz {0} {1} a cada:</VEF_WhileCaravaning>
  <VCE_AffectsAllAnimalMods>Essas opções de comportamento animal afetarão todos os mods animais que compartilham código do Vanilla Expanded Framework</VCE_AffectsAllAnimalMods>
  <VCE_CorpseDecayingEffectOption>Permitir mecânica de decomposição de cadáveres (por exemplo, efeito da lesma Helixien)</VCE_CorpseDecayingEffectOption>
  <VCE_DigWhenHungryOption>Permitir escavar quando mecânicos famintos (por exemplo, Frostmites cavando cadáveres)</VCE_DigWhenHungryOption>
  <VCE_DigPeriodicallyOption>Permite que os animais cavem coisas periodicamente</VCE_DigPeriodicallyOption>
  <VCE_AnimalParticlesOption>Permitir partículas de animais (gás e sujeira)</VCE_AnimalParticlesOption>
  <VCE_AsexualReproductionOption>Permitir reprodução assexuada</VCE_AsexualReproductionOption>
  <VFE_AsexualReproductionDisabled>Reprodução assexuada desativada por meio de opções de mod</VFE_AsexualReproductionDisabled>
  <VCE_BlinkMechanicsOption>Permitir mecânica de "piscar" (por exemplo, Skiphounds)</VCE_BlinkMechanicsOption>
  <VCE_BuildPeriodicallyOption>Permitir que animais construam coisas (por exemplo, castores constroem represas)</VCE_BuildPeriodicallyOption>
  <VCE_ChargeBatteriesOption>Permitir que animais recarreguem baterias próximas ou reabasteçam</VCE_ChargeBatteriesOption>
  <VCE_ExplodingEggsOption>Permitir ovos de animais que explodem (como os de dragões)</VCE_ExplodingEggsOption>
  <VCE_HoveringOption>Permitir que os animais “pairem”, ignorando os custos de movimentação do terreno e passeios na água</VCE_HoveringOption>
  <VCE_GraphicChangingOption>Permitir que animais alterem gráficos (por exemplo, Chameleon Yak)</VCE_GraphicChangingOption>
  <VCE_EffecterOption>Permite que animais causem pensamentos, estados mentais ou pensamentos</VCE_EffecterOption>
  <VCE_RegenerationOption>Permitir regeneração de saúde (ativa e passiva)</VCE_RegenerationOption>
  <VCE_ResurrectionOption>Permitir que os animais ressuscitem automaticamente (por exemplo, Phoenix Owlcat)</VCE_ResurrectionOption>
  <VCE_UntameableOption>Permitir que alguns animais sejam indomáveis</VCE_UntameableOption>
  <VEF_AnimalsSearch>Procurar:</VEF_AnimalsSearch>
  <VEF_BillRequiresMass>Requer {0} Kg de massa total</VEF_BillRequiresMass>
</LanguageData>
