<?xml version="1.0" encoding="utf-8"?>
<LanguageData>
  <NamerFactionEmpire.rulePack.rulesStrings.0>r_name(p=3)-&gt;白泉飯店</NamerFactionEmpire.rulePack.rulesStrings.0>
  <NamerFactionEmpire.rulePack.rulesStrings.1>r_name(p=2)-&gt;白泉地堡</NamerFactionEmpire.rulePack.rulesStrings.1>
  <NamerFactionEmpire.rulePack.rulesStrings.2>r_name(p=3)-&gt;英克雷</NamerFactionEmpire.rulePack.rulesStrings.2>
  <NamerFactionEmpire.rulePack.rulesStrings.3>r_name(p=2)-&gt;阿巴拉契亞飛地</NamerFactionEmpire.rulePack.rulesStrings.3>
  <NamerFactionEmpire.rulePack.rulesStrings.4>r_name(p=1)-&gt;白泉飛地</NamerFactionEmpire.rulePack.rulesStrings.4>
  <NamerFactionEmpire.rulePack.rulesStrings.5>r_name(p=1)-&gt;阿巴拉契亞地堡</NamerFactionEmpire.rulePack.rulesStrings.5>
</LanguageData>
