<?xml version="1.0" encoding="utf-8"?>
<LanguageData>
  <FCP_Apparel_BoS_Appalachia_Fatigues.description>Standard-issue 钢铁兄弟会 fatigues. Made from a robust and durable material, these fatigues are worn by members of the Brotherhood during their daily operations in Appalachia.</FCP_Apparel_BoS_Appalachia_Fatigues.description>
  <FCP_Apparel_BoS_Appalachia_Fatigues.label>BoS 阿巴拉契亚疲劳</FCP_Apparel_BoS_Appalachia_Fatigues.label>
  <FCP_Apparel_BoS_Appalachia_Infantry_Uniform.description>A pristine military dress uniform worn by Brotherhood infantry during formal occasions. The uniform bears the insignia of the 钢铁兄弟会 and represents the discipline and order of the organization.</FCP_Apparel_BoS_Appalachia_Infantry_Uniform.description>
  <FCP_Apparel_BoS_Appalachia_Infantry_Uniform.label>BoS 阿巴拉契亚步兵制服</FCP_Apparel_BoS_Appalachia_Infantry_Uniform.label>
  <FCP_Apparel_BoS_B35C_Armor.description>A vacuum-sealed asbestos jumpsuit covering the entire body. Its purpose is twof老旧: it allows the user to actually operate the armor and protect soft tissue from moving parts inside the suit and heat. Unlike the BOS uniform, the Recon Armor provides decent protection on its own and is often used by Brotherhood agents on scouting missions or other situations where the clunky and loud power armor would draw too much attention.</FCP_Apparel_BoS_B35C_Armor.description>
  <FCP_Apparel_BoS_B35C_Armor.label>BoS B35C 装甲</FCP_Apparel_BoS_B35C_Armor.label>
  <FCP_Apparel_BoS_Battle_Coat.description>兄弟会军官穿的坚固的军大衣。这件外套带有兄弟会的徽章，旨在承受严酷的战斗，同时保持专业的外观。</FCP_Apparel_BoS_Battle_Coat.description>
  <FCP_Apparel_BoS_Battle_Coat.label>BoS 战斗外套</FCP_Apparel_BoS_Battle_Coat.label>
  <FCP_Apparel_BoS_Bomber_Jacket.description>兄弟会飞行员和飞鸟机组成员穿着的皮革飞行夹克。该夹克带有兄弟会的装备和剑徽记，并在飞行操作期间提供保护。</FCP_Apparel_BoS_Bomber_Jacket.description>
  <FCP_Apparel_BoS_Bomber_Jacket.label>BoS 飞行员夹克</FCP_Apparel_BoS_Bomber_Jacket.label>
  <FCP_Apparel_BoS_Brotherhood_Fatigues.description>Standard-issue field uniform of the 钢铁兄弟会. These durable fatigues are worn by enlisted personnel and junior officers during daily operations and provide basic protection against environmental hazards.</FCP_Apparel_BoS_Brotherhood_Fatigues.description>
  <FCP_Apparel_BoS_Brotherhood_Fatigues.label>BoS 兄弟会疲劳</FCP_Apparel_BoS_Brotherhood_Fatigues.label>
  <FCP_Apparel_BoS_Brotherhood_Field_Medic_Fatigues.description>兄弟会战地医务人员穿着的专业医疗制服。迷彩服设有额外的口袋，可存放医疗用品，旨在防止伤员治疗过程中的污染。</FCP_Apparel_BoS_Brotherhood_Field_Medic_Fatigues.description>
  <FCP_Apparel_BoS_Brotherhood_Field_Medic_Fatigues.label>BoS 兄弟会战地军医疲劳</FCP_Apparel_BoS_Brotherhood_Field_Medic_Fatigues.label>
  <FCP_Apparel_BoS_Classic_Combat_Armor_Reinforced.description>Enhanced combat armor upgraded with 钢铁兄弟会 technology. This armor retains the design of the original while incorporating improved protection and environmental sealing systems.</FCP_Apparel_BoS_Classic_Combat_Armor_Reinforced.description>
  <FCP_Apparel_BoS_Classic_Combat_Armor_Reinforced.label>BoS 强化战斗装甲</FCP_Apparel_BoS_Classic_Combat_Armor_Reinforced.label>
  <FCP_Apparel_BoS_Elder_Robes.description>Ceremonial robes worn by Brotherhood Elders. These robes symbolize the authority and responsibility that comes with leading the 钢铁兄弟会 in their sacred mission to preserve technology.</FCP_Apparel_BoS_Elder_Robes.description>
  <FCP_Apparel_BoS_Elder_Robes.label>BoS长老长袍</FCP_Apparel_BoS_Elder_Robes.label>
  <FCP_Apparel_BoS_Field_Scribe.description>兄弟会抄写员在兄弟会设施安全之外执行研究任务时所穿的野战制服。该制服将学术传统与实际领域的要​​求结合起来。</FCP_Apparel_BoS_Field_Scribe.description>
  <FCP_Apparel_BoS_Field_Scribe.label>BoS 现场抄写员制服</FCP_Apparel_BoS_Field_Scribe.label>
  <FCP_Apparel_BoS_Jumpsuit.description>一款从头开始设计的连身衣，可与 West Tek 动力装甲框架配合使用。它是一款合身的套装，旨在在操作装甲时提供最大的舒适度和实用性。虽然这不是操作装甲的要求，但它使长期使用更加舒适并减少擦伤。</FCP_Apparel_BoS_Jumpsuit.description>
  <FCP_Apparel_BoS_Jumpsuit.label>BoS 连身裤</FCP_Apparel_BoS_Jumpsuit.label>
  <FCP_Apparel_BoS_Lancer_Captain_Uniform.description>A formal dress uniform worn by Lancer Captains of the 钢铁兄弟会. The uniform features g老旧 braiding and ceremonial shoulder boards, marking the wearer as an officer of the Brotherhood's air fleet.</FCP_Apparel_BoS_Lancer_Captain_Uniform.description>
  <FCP_Apparel_BoS_Lancer_Captain_Uniform.label>BoS Lancer 队长制服</FCP_Apparel_BoS_Lancer_Captain_Uniform.label>
  <FCP_Apparel_BoS_Outcast_Recon_Armor.description>兄弟会流亡者侦察兵和先遣队穿着的专门侦察装甲。该装甲经过改进，具有增强的机动性系统和隐身增强功能，具有独特的流放者标记和战术修改，反映了他们更具侵略性的作战原则。</FCP_Apparel_BoS_Outcast_Recon_Armor.description>
  <FCP_Apparel_BoS_Outcast_Recon_Armor.label>BoS 流亡者侦察装甲</FCP_Apparel_BoS_Outcast_Recon_Armor.label>
  <FCP_Apparel_BoS_Outcast_Scribe_Robes.description>兄弟会弃儿专家和技术人员穿着的功能性长袍。这些长袍具有独特的流放者色彩和徽章，经过修改，适合学者和工程师与战士一起追求技术霸权的野外行动。</FCP_Apparel_BoS_Outcast_Scribe_Robes.description>
  <FCP_Apparel_BoS_Outcast_Scribe_Robes.label>BoS 流放抄写员长袍</FCP_Apparel_BoS_Outcast_Scribe_Robes.label>
  <FCP_Apparel_BoS_Recon_Armor.description>兄弟会侦察部队使用的轻型战术装甲。侦察装甲提供坚实的保护，同时保持机动性和隐身能力，使其成为侦察任务和全动力装甲不切实际的情况的理想选择。采用先进的复合材料和集成传感器系统。</FCP_Apparel_BoS_Recon_Armor.description>
  <FCP_Apparel_BoS_Recon_Armor.label>BoS 侦察装甲</FCP_Apparel_BoS_Recon_Armor.label>
  <FCP_Apparel_BoS_Science_Scribe.description>Laboratory attire worn by Science Scribes of the 钢铁兄弟会. The clean, white coat is designed for work with 危险 pre-war technology and experimental equipment.</FCP_Apparel_BoS_Science_Scribe.description>
  <FCP_Apparel_BoS_Science_Scribe.label>BoS 科学抄写员服装</FCP_Apparel_BoS_Science_Scribe.label>
  <FCP_Apparel_BoS_Scribe_Robes.description>兄弟会文士在正式仪式上穿着的连帽长袍。这些长袍代表了抄写员会的学术传统以及他们对保存技术知识的奉献精神。</FCP_Apparel_BoS_Scribe_Robes.description>
  <FCP_Apparel_BoS_Scribe_Robes.label>BoS 抄写长袍</FCP_Apparel_BoS_Scribe_Robes.label>
  <FCP_Apparel_BoS_Squire.description>兄弟会侍从所穿的训练服。这款实用的服装专为战斗训练和教育而设计，同时标志着穿着者在兄弟会等级制度中的初级地位。</FCP_Apparel_BoS_Squire.description>
  <FCP_Apparel_BoS_Squire.label>BoS 乡绅制服</FCP_Apparel_BoS_Squire.label>
</LanguageData>
