<?xml version="1.0" encoding="utf-8" ?>
<LanguageData>

        <!--__________ Вступление во фракции: текст письма __________-->

        <!--_____ Анклав _____-->

        <!-- Параметры вступления -->

        <FCP_Enclave_Enlist_Letter_Title>Вы вступили в армию {FACTION_name}.</FCP_Enclave_Enlist_Letter_Title>
        <FCP_Enclave_Enlist_Letter_Label>Это прямое сообщение от вашего командира. Это честь — служить в армии {FACTION_name}. Будьте готовы явиться на любую из наших баз или городов для повышения квалификации.\n\n Вам будет начислено стандартное жалованье каждую неделю на вас и ваших солдат, а также провизия, которую можно забрать на наших базах. Военные объекты {FACTION_name} — первоклассные американские базы для подготовки ваших войск. Используйте их с умом.\n\n Лучшая Америка стоит того, чтобы за неё сражаться!</FCP_Enclave_Enlist_Letter_Label>
        <FCP_Enclave_Enlist_Button_Label>Вступить в {FACTION_name}.</FCP_Enclave_Enlist_Button_Label>
        <FCP_Enclave_Enlist_Button_Desc>Подписать новый контракт с {FACTION_name}.</FCP_Enclave_Enlist_Button_Desc>
        <FCP_Enclave_Enlist_Requrements_Not_Satisfied>Необходимо иметь не менее 10 расположения, сейчас у вас только {0}.</FCP_Enclave_Enlist_Requrements_Not_Satisfied>
        <FCP_Enclave_Enlisted_With_Key>Вступил в: {FACTION_name}</FCP_Enclave_Enlisted_With_Key>
        <FCP_Active_Enlist_Options>Активные параметры вступления</FCP_Active_Enlist_Options>

        <!-- Задания -->

        <FCP_Enclave_Missions_Label>Задания</FCP_Enclave_Missions_Label>
        <FCP_Enclave_Missions_Desc>Описания заданий</FCP_Enclave_Missions_Desc>
        <FCP_Enclave_Menu_Missions_Desc>Покидая штаб, вы расспрашиваете о потенциальных заданиях, которые нужно выполнить.</FCP_Enclave_Menu_Missions_Desc>
        <FCP_Enclave_Menu_Missions_Select_Quest>Выберите задание: </FCP_Enclave_Menu_Missions_Select_Quest>
        <FCP_Enclave_Menu_Missions_Start_Quest>Начать задание ({0})</FCP_Enclave_Menu_Missions_Start_Quest>
        <FCP_Cancel>Отмена</FCP_Cancel>
        <FCP_Enclave_Not_Enough_Money>Недостаточно денег</FCP_Enclave_Not_Enough_Money>

        <!-- Жалованье -->

        <FCP_Enclave_Salary_Label>Жалованье</FCP_Enclave_Salary_Label>
        <FCP_Enclave_Salary_Desc>Вы имеете право получать жалованье от этой фракции каждые 14 дней.</FCP_Enclave_Salary_Desc>

        <!-- Провизия -->

        <FCP_Enclave_Provisions_Label>Провизия</FCP_Enclave_Provisions_Label>
        <FCP_Enclave_Provisions_Desc>Провизия будет доставляться через инвентарь вашего каравана каждые 10 дней:\n\n- 2 продовольственных ящика Анклава \n- ×1 медицинский ящик Анклава</FCP_Enclave_Provisions_Desc>

        <FCP_Enclave_Provisions_Label_Standard_Issue>Стандартное снаряжение</FCP_Enclave_Provisions_Label_Standard_Issue>
        <FCP_Enclave_Provisions_Desc_Standard_Issue>Стандартное снаряжение Анклава будет доставлено через инвентарь вашего каравана каждые 30 дней:\n\n- ×1 оружейный ящик Анклава \n- ×1 ящик с формой Анклава</FCP_Enclave_Provisions_Desc_Standard_Issue>

        <!-- Склад -->

        <FCP_Enclave_Storage_Label>Склад</FCP_Enclave_Storage_Label>
        <FCP_Enclave_Storage_Desc>Храните предметы из каравана на складе фракции. Фракционные склады доступны на всех форпостах фракции, и их содержимое сохраняется, даже если вы больше не состоите во фракции.</FCP_Enclave_Storage_Desc>
        <FCP_Enclave_Storage_Inventory>Инвентарь склада</FCP_Enclave_Storage_Inventory>
        <FCP_Enclave_Caravan_Inventory>Инвентарь каравана</FCP_Enclave_Caravan_Inventory>

        <!-- Работа -->

        <FCP_Enclave_Hospital_Label>Госпиталь</FCP_Enclave_Hospital_Label>
        <FCP_Enclave_Hospital_Desc>Обратитесь в госпиталь этой базы. Эта услуга обеспечивает лечение всех ваших солдат промышленной медициной. Иммунитет также повышается быстрее, пока ваши солдаты находятся в госпитале.</FCP_Enclave_Hospital_Desc>
        <FCP_Enclave_Intellectual_Training_Label>Тренировка: научные исследования</FCP_Enclave_Intellectual_Training_Label>
        <FCP_Enclave_Intellectual_Training_Desc>Тренируйте своих солдат с почасовым набором опыта в следующих навыках:\n\n- Интеллект\n\nПочасовой набор опыта прекращается, когда фракция отдыхает ночью.</FCP_Enclave_Intellectual_Training_Desc>
        <FCP_Enclave_Shooting_Training_Label>Тренировка: базовая боевая подготовка</FCP_Enclave_Shooting_Training_Label>
        <FCP_Enclave_Shooting_Training_Desc>Тренируйте своих солдат с почасовым набором опыта в следующих навыках:\n\n- Стрельба, Ближний бой \n\nПочасовой набор опыта прекращается, когда фракция отдыхает ночью.</FCP_Enclave_Shooting_Training_Desc>

        <!-- Увольнение -->

        <FCP_Enclave_Resign_Menu_Text>Вы немедленно покинете действующую службу в армии Анклава. (-25 к отношениям)</FCP_Enclave_Resign_Menu_Text>
        <FCP_Enclave_Resign_Letter_Title>Уволен</FCP_Enclave_Resign_Letter_Title>
        <FCP_Enclave_Resign_Letter_Label>Уволиться</FCP_Enclave_Resign_Letter_Label>
        <FCP_Enclave_Resign_Button_Label>Вы успешно покинули действующую службу в армии Анклава. (-25 к отношениям)</FCP_Enclave_Resign_Button_Label>
        <FCP_Enclave_Resign_Button_Desc>Покинуть действующую службу в этой фракции.</FCP_Enclave_Resign_Button_Desc>
        <FCP_Enclave_Player_Settlement_Required>Требуется поселение игрока</FCP_Enclave_Player_Settlement_Required>
        <FCP_Enclave_Enlisted_To_Hostile_Faction>невозможно вступить, так как вы состоите во враждебной фракции — {HOSTILEFACTION_name}</FCP_Enclave_Enlisted_To_Hostile_Faction>

        <!-- Исключение -->

        <FCP_Enclave_Kick_Out_Letter_Title>Исключён</FCP_Enclave_Kick_Out_Letter_Title>
        <FCP_Enclave_Kick_Out_Label_Title>Прямой приказ о немедленном расторжении вашего контракта подписан {LEADER_nameDef}. Вы были исключены из армии {FACTION_name}.</FCP_Enclave_Kick_Out_Label_Title>

        <!-- Подкрепление -->

        <FCP_Enclave_Reinforcements_Button_Label>Подкрепление</FCP_Enclave_Reinforcements_Button_Label>
        <FCP_Enclave_Reinforcements_Button_Desc>Запросить подкрепление от вашей фракции. Количество солдат зависит от текущих отношений.</FCP_Enclave_Reinforcements_Button_Desc>

</LanguageData>