<?xml version="1.0" encoding="utf-8"?>
<LanguageData>
  <VFE_ChoosePropCategory>Valitse tarjousluokka:</VFE_ChoosePropCategory>
  <VFE_GoBack>Mene takaisin</VFE_GoBack>
  <VFE_PrefabSearch>Haku</VFE_PrefabSearch>
  <VFE_NoSilver>Varastoissa ei ole tarpeeksi hopeaa. Sinulla on oltava vähintään {0} hopeaa rakentaaksesi tämän rekvisiitin</VFE_NoSilver>
  <VFE_PropCostMultiplier>Prop kustannuskerroin</VFE_PropCostMultiplier>
  <VFE_PropCostMultiplierDesc>Hopealla ostettujen elementtien hinta lasketaan niiden koon, osumapisteiden ja peitteen mukaan. Tällä liukusäätimellä voit muuttaa niiden maksamisen. 0 poistaa kaikki hopeakustannukset käytöstä.</VFE_PropCostMultiplierDesc>
  <VFE_SilverReturnMultiplier>Hopean tuottokerroin</VFE_SilverReturnMultiplier>
  <VFE_SilverReturnMultiplierDesc>Kun rekvisiitta tuhoutuu, se palauttaa ostohintansa hopeana. Oletuksena tämä on 100 % tästä hinnasta, mutta sitä voidaan vähentää tällä asetuksella.</VFE_SilverReturnMultiplierDesc>
  <VFE_Reset>Nollaa</VFE_Reset>
  <VPE_NeedsMats>Rakennettu</VPE_NeedsMats>
  <VPE_NeedsMatsDesc>Tämä rekvisiitta tarvitsee rakennusmateriaaleja hopean sijasta, ja kolonistien on rakennettava se itse</VPE_NeedsMatsDesc>
  <VFEPD_BuildProps>rakentaa rekvisiitta</VFEPD_BuildProps>
  <VFEPD_BuildPropsDesc>Avaa valikko ja rakenna rekvisiitta hopeahintaan.</VFEPD_BuildPropsDesc>
  <VFEPD_ResearchNeeded>Ei voida rakentaa ennen kuin siirtokunta on tutkinut kohteen {0}</VFEPD_ResearchNeeded>
  <VFEPD_MakeCopy>Tee kopio</VFEPD_MakeCopy>
  <VFEPD_MakeCopyDesc>Tee kopio tästä rekvisiittasta. Tämä edellyttää, että potkurin hopeahinta on saatavilla varastossa.</VFEPD_MakeCopyDesc>
</LanguageData>
