<?xml version="1.0" encoding="utf-8"?>
<LanguageData>
  <Spaceports_RoyaltyShuttle.label>Vennaskonna vertilind</Spaceports_RoyaltyShuttle.label>
  <Spaceports_ShuttleA.label>vertilind</Spaceports_ShuttleA.label>
  <Spaceports_ShuttleB.label>vertilind</Spaceports_ShuttleB.label>
  <Spaceports_ShuttleC.label>vertilind</Spaceports_ShuttleC.label>
  <Spaceports_ShuttleD.label>vertilind</Spaceports_ShuttleD.label>
  <Spaceports_ShuttleE.label>vertilind</Spaceports_ShuttleE.label>
  <Spaceports_ShuttleF.label>vertilind</Spaceports_ShuttleF.label>
  <Spaceports_ShuttleG.label>vertilind</Spaceports_ShuttleG.label>
  <Spaceports_ShuttleH.label>vertilind</Spaceports_ShuttleH.label>
  <Spaceports_ShuttleI.label>vertilind</Spaceports_ShuttleI.label>
  <Spaceports_ShuttleInert.label>maandatud vertibird</Spaceports_ShuttleInert.label>
  <Spaceports_ShuttleJ.label>vertilind</Spaceports_ShuttleJ.label>
  <Spaceports_ShuttleK.label>vertilind</Spaceports_ShuttleK.label>
  <Spaceports_ShuttleSkip.label>vertilind</Spaceports_ShuttleSkip.label>
  <Spaceports_SurpriseShuttle.label>tundmatu vertilind</Spaceports_SurpriseShuttle.label>
  <VFED_Ship_DeserterShuttle.label>vertibird</VFED_Ship_DeserterShuttle.label>
  <VFEE_Ship_ArmoredShuttle.label>XVB02</VFEE_Ship_ArmoredShuttle.label>
  <Ship_Shuttle.label>Whitespring Vertibird</Ship_Shuttle.label>
</LanguageData>
