<?xml version="1.0" encoding="utf-8"?>
<LanguageData>
  <Outpost_Artillery.description>放置一个临时的、自主领导的营地，专门通过炮击为附近的定居点提供点防御。每个典当的任务是维护和使用迫击炮。弹幕用完后，需要一天时间准备新的弹幕。</Outpost_Artillery.description>
  <Outpost_Artillery.label>炮兵前哨</Outpost_Artillery.label>
  <Outpost_Defensive.description>放置一个临时的、自主领导的营地，专门拦截和伏击敌人对主要殖民地的袭击。在前哨基地赢得一场 s商场 小冲突可以显着减少敌人对主要殖民地的袭击规模。此外，防御性前哨站的任务是向主要殖民地发送空投舱，进行临时通知防御。</Outpost_Defensive.description>
  <Outpost_Defensive.label>防御前哨</Outpost_Defensive.label>
  <Outpost_Drilling.description>放置一个临时的、自主领导的营地，专门负责定位和开采地下化学燃料库。一旦收集到足够的数量，就会在派系主要殖民地的郊区进行交付。</Outpost_Drilling.description>
  <Outpost_Drilling.label>钻井前哨站</Outpost_Drilling.label>
  <Outpost_Encampment.description>放置一个临时的、自主领导的营地，作为商队的休息点。露营时，所有棋子都会恢复食物和休息，并留出时间治愈伤势。</Outpost_Encampment.description>
  <Outpost_Encampment.label>扎营</Outpost_Encampment.label>
  <Outpost_Farming.description>放置一个临时的、自主领导的营地，专门用于播种和收获容易生长的植被，不能放置在沙漠上。一旦收集到足够的数量，就会在派系主要殖民地的郊区进行交付。</Outpost_Farming.description>
  <Outpost_Farming.label>农业前哨</Outpost_Farming.label>
  <Outpost_Hunting.description>建立一个临时的、自治的营地，专门从事狩猎和屠宰野生动物。一旦收集到足够的数量，就会在派系主要殖民地的郊区进行交付。</Outpost_Hunting.description>
  <Outpost_Hunting.label>狩猎前哨</Outpost_Hunting.label>
  <Outpost_Logging.description>放置一个临时的、自治的营地，专门从该地区的树木中收集木材，不能放置在沙漠上。一旦收集到足够的数量，就会在派系主要殖民地的郊区进行交付。</Outpost_Logging.description>
  <Outpost_Logging.label>伐木前哨</Outpost_Logging.label>
  <Outpost_Mining.description>放置一个临时的、自治的营地，专门收集和加工石头或金属，只能放置在丘陵或山脉上。一旦收集到足够的数量，就会在派系主要殖民地的郊区进行交付。</Outpost_Mining.description>
  <Outpost_Mining.label>采矿前哨站</Outpost_Mining.label>
  <Outpost_Production.description>建立一个临时的、自主领导的营地，专门从事机械和电子元件的制造和制造。一旦生产出足够的数量，就会在派系主要殖民地的郊区进行交付。</Outpost_Production.description>
  <Outpost_Production.label>生产前哨</Outpost_Production.label>
  <Outpost_Scavenging.description>放置一个临时的、自主领导的营地，专门负责侦察附近未标记的定居点以及其中包含的战利品。一旦收集到一些值得注意的东西，就会在派系主要殖民地的郊区进行交付。</Outpost_Scavenging.description>
  <Outpost_Scavenging.label>拾荒前哨</Outpost_Scavenging.label>
  <Outpost_Science.description>设立一个临时的、自主领导的营地，专门从事研究和分析。获得的任何信息都将与整个派系共享。</Outpost_Science.description>
  <Outpost_Science.label>科学前哨站</Outpost_Science.label>
  <Outpost_Town.description>放置一个临时的、自治的城镇，旨在为旅行者和商人提供热情好客的服务。如果游客觉得他们的住所很友好，他们将被邀请作为永久居民加入该镇。仅当 10 格内有 3 个预先存在的定居点时，才能建立城镇。</Outpost_Town.description>
  <Outpost_Town.label>镇</Outpost_Town.label>
  <Outpost_Trading.description>放置一个临时的、自治的营地，专门与流浪者、商队和当地人进行销售和易货贸易，以换取白银。一旦收集到足够的数量，就会在派系主要殖民地的郊区进行交付。</Outpost_Trading.description>
  <Outpost_Trading.label>贸易前哨</Outpost_Trading.label>
</LanguageData>
