<?xml version="1.0" encoding="utf-8"?>
<LanguageData>
  <FCP_Culture_BoS.description>鋼鐵兄弟會保持嚴格的軍事紀律和對戰前技術的尊重。成員遵循法典，重視指揮系統，並將自己視為野蠻世界中知識的保護者。</FCP_Culture_BoS.description>
  <FCP_Culture_BoS.label>鋼鐵兄弟會章節</FCP_Culture_BoS.label>
  <FCP_Culture_BoS_Outcasts.description>流亡者是純粹主義者，他們拒絕接受里昂長老對法典的偏離。他們完全致力於取得和保存技術，最多將外來者視為障礙。使命就是一切。</FCP_Culture_BoS_Outcasts.description>
  <FCP_Culture_BoS_Outcasts.label>鋼鐵流亡者兄弟會</FCP_Culture_BoS_Outcasts.label>
  <FCP_Culture_Lyons_BoS.description>萊昂斯長老的分會脫離了法典，以幫助首都廢土的人民。他的追隨者將兄弟會紀律與同情心結合起來，相信科技應該為人類服務，而不是被人類囤積起來。</FCP_Culture_Lyons_BoS.description>
  <FCP_Culture_Lyons_BoS.label>鋼鐵兄弟會里昂</FCP_Culture_Lyons_BoS.label>
</LanguageData>
