<?xml version="1.0" encoding="utf-8"?>
<LanguageData>
  <FCP_Animal_German_Shepherd_Dog.description>일부 개는 야생이어서 폐기물을 괴롭히고 가축을 죽이지만, 고군분투하는 많은 황무지 사람들에게는 길들인 개들이 필요합니다. 또한 두 발로 걷는 동물에 대한 동반자 역할을 하는 국내 품종의 경우도 드물다. 인간과 슈퍼 돌연변이는 이 개과를 진정으로 길들이고 길들이는 것으로 알려진 유일한 종입니다.</FCP_Animal_German_Shepherd_Dog.description>
  <FCP_Animal_German_Shepherd_Dog.label>독일 셰퍼드 개</FCP_Animal_German_Shepherd_Dog.label>
  <FCP_Animal_Minutemen_Guard_Dog.description>일부 개는 야생이어서 폐기물을 괴롭히고 가축을 죽이지만, 고군분투하는 많은 황무지 사람들에게는 길들인 개들이 필요합니다. 독일 셰퍼드와 같은 국내 품종이 이족 보행 동물에 대한 동반자 역할을 하는 경우도 드물다. 특히 보스턴 폐허 주변의 미닛맨(Minutemen)은 그들을 군대의 경비견과 작업견으로 사용했습니다.</FCP_Animal_Minutemen_Guard_Dog.description>
  <FCP_Animal_Minutemen_Guard_Dog.label>미닛맨 경비견</FCP_Animal_Minutemen_Guard_Dog.label>
  <FCP_Animal_Nightstalker.description>전쟁 전 유전자 실험의 끔찍한 산물인 밤추적자는 코요테와 방울뱀의 DNA를 결합한 잡종 생물입니다. 이 은밀한 포식자들은 어둠 속에서 무리를 지어 사냥하며 독을 이용해 먹이를 쓰러뜨립니다. 그들은 개과의 무리 지능과 뱀의 은밀함 및 독을 결합하여 황무지에서 가장 두려운 포식자 중 하나가 되었습니다. 그들의 독특한 실루엣과 빛나는 눈은 그들을 만나는 사람들에게 공포를 안겨줍니다.</FCP_Animal_Nightstalker.description>
  <FCP_Animal_Nightstalker.label>나이트스토커</FCP_Animal_Nightstalker.label>
  <FCP_Animal_Nightstalker.tools.0.label>독이 있는 물린</FCP_Animal_Nightstalker.tools.0.label>
  <FCP_Animal_Nightstalker.tools.1.label>집게발</FCP_Animal_Nightstalker.tools.1.label>
  <FCP_Animal_Nightstalker.tools.2.label>머리</FCP_Animal_Nightstalker.tools.2.label>
  <FCP_Animal_Vicious_Dog.description>악랄한 개(Vicious dogs)는 거의 털이 없고 부분적으로 구울화된 황무지 개과의 종입니다. 황무지의 무자비한 생존자인 이 굶주리고 방사선에 노출된 똥개는 움직이는 모든 것을 공격합니다.</FCP_Animal_Vicious_Dog.description>
  <FCP_Animal_Vicious_Dog.label>악랄한 개</FCP_Animal_Vicious_Dog.label>
  <FCP_Animal_Vicious_Guard_Dog.description>악랄한 개(Vicious dogs)는 거의 털이 없고 부분적으로 구울화된 황무지 개과의 종입니다. 황무지의 무자비한 생존자인 이 굶주리고 방사선에 노출된 똥개는 움직이는 모든 것을 공격합니다. 일부 개는 가축화되었으며 심지어 주인과 모든 재산을 보호하는 임무를 맡게 되었습니다. 이 동물은 최선을 다해 그렇게 할 것입니다.</FCP_Animal_Vicious_Guard_Dog.description>
  <FCP_Animal_Vicious_Guard_Dog.label>악랄한 개</FCP_Animal_Vicious_Guard_Dog.label>
</LanguageData>
