<?xml version="1.0" encoding="utf-8"?>
<LanguageData>
  <VAEI_DeepTalkQuestion.stages.0.label>un discours profond ?</VAEI_DeepTalkQuestion.stages.0.label>
  <VAEI_DirtyRoom.stages.0.description>La pièce dans laquelle je me trouve est légèrement sale. Cela me fait peur.</VAEI_DirtyRoom.stages.0.description>
  <VAEI_DirtyRoom.stages.0.label>environnement un peu sale</VAEI_DirtyRoom.stages.0.label>
  <VAEI_DirtyRoom.stages.1.description>La pièce dans laquelle je me trouve est sale. Cela me répugne.</VAEI_DirtyRoom.stages.1.description>
  <VAEI_DirtyRoom.stages.1.label>environnement sale</VAEI_DirtyRoom.stages.1.label>
  <VAEI_DirtyRoom.stages.2.description>La pièce dans laquelle je me trouve est incroyablement sale. Je dois le quitter le plus tôt possible.</VAEI_DirtyRoom.stages.2.description>
  <VAEI_DirtyRoom.stages.2.label>environnement très sale</VAEI_DirtyRoom.stages.2.label>
  <VAEI_Gagged.stages.0.description>Hmpff, huff hmphhhh</VAEI_Gagged.stages.0.description>
  <VAEI_Gagged.stages.0.label>bâillonné</VAEI_Gagged.stages.0.label>
  <VAEI_KindWordsQuestion.stages.0.description>Je pense que j’ai reçu des mots gentils. Je pense.</VAEI_KindWordsQuestion.stages.0.description>
  <VAEI_KindWordsQuestion.stages.0.label>des mots gentils ?</VAEI_KindWordsQuestion.stages.0.label>
  <VAEI_KindWordsQuestionMemory.stages.0.label>des mots gentils ?</VAEI_KindWordsQuestionMemory.stages.0.label>
  <VAEI_MockedMemory.stages.0.label>moqué</VAEI_MockedMemory.stages.0.label>
  <VAEI_MockedMood.stages.0.description>Mes insécurités ont été moquées ! Quelle méchante personne !</VAEI_MockedMood.stages.0.description>
  <VAEI_MockedMood.stages.0.label>moqué</VAEI_MockedMood.stages.0.label>
  <VAEI_MoodSwing.stages.0.description>Je ressens un doux bonheur, comme un sourire tranquille qui se répand dans ma journée.</VAEI_MoodSwing.stages.0.description>
  <VAEI_MoodSwing.stages.0.label>pensées heureuses</VAEI_MoodSwing.stages.0.label>
  <VAEI_MoodSwing.stages.1.description>Je surfe sur une vague de joie et de positivité, me sentant vraiment heureuse et contente.</VAEI_MoodSwing.stages.1.description>
  <VAEI_MoodSwing.stages.1.label>pensées très heureuses</VAEI_MoodSwing.stages.1.label>
  <VAEI_MoodSwing.stages.2.description>Je me sens accablé par une tristesse dont il est difficile de se débarrasser.</VAEI_MoodSwing.stages.2.description>
  <VAEI_MoodSwing.stages.2.label>pensées tristes</VAEI_MoodSwing.stages.2.label>
  <VAEI_MoodSwing.stages.3.description>Mon cœur se sent écrasé par une tristesse intense et profonde, presque trop lourde à supporter.</VAEI_MoodSwing.stages.3.description>
  <VAEI_MoodSwing.stages.3.label>pensées très tristes</VAEI_MoodSwing.stages.3.label>
  <VAEI_Rehumanized.stages.0.description>C’est tellement bon de se sentir enfin à nouveau normal. Eh bien, c'est plutôt normal.</VAEI_Rehumanized.stages.0.description>
  <VAEI_Rehumanized.stages.0.label>réhumanisé</VAEI_Rehumanized.stages.0.label>
  <VAEI_Restrained.stages.0.description>Je veux enlever cette camisole de force ! Je ne peux rien faire !</VAEI_Restrained.stages.0.description>
  <VAEI_Restrained.stages.0.label>restreint</VAEI_Restrained.stages.0.label>
  <VAEI_SanityEffectWithInhumanized.stages.0.description>La clarté transperce comme un couteau. La vérité banale est douloureusement ennuyeuse.</VAEI_SanityEffectWithInhumanized.stages.0.description>
  <VAEI_SanityEffectWithInhumanized.stages.0.label>pensées saines</VAEI_SanityEffectWithInhumanized.stages.0.label>
  <VAEI_SanityEffectWithInhumanized.stages.1.description>Le doute s’installe, remettant en question le chaos. Pourquoi cette clarté ressemble-t-elle à des chaînes ?</VAEI_SanityEffectWithInhumanized.stages.1.description>
  <VAEI_SanityEffectWithInhumanized.stages.1.label>des doutes raisonnables</VAEI_SanityEffectWithInhumanized.stages.1.label>
  <VAEI_SanityEffectWithInhumanized.stages.2.description>Des sentiments de normalité me rongent l’esprit, effaçant la belle folie.</VAEI_SanityEffectWithInhumanized.stages.2.description>
  <VAEI_SanityEffectWithInhumanized.stages.2.label>des sentiments sains</VAEI_SanityEffectWithInhumanized.stages.2.label>
  <VAEI_SanityEffectWithoutInhumanized.stages.0.description>Le monde commence à se plier sur ses bords ; la réalité semble moins certaine.</VAEI_SanityEffectWithoutInhumanized.stages.0.description>
  <VAEI_SanityEffectWithoutInhumanized.stages.0.label>santé mentale affectée</VAEI_SanityEffectWithoutInhumanized.stages.0.label>
  <VAEI_SanityEffectWithoutInhumanized.stages.1.description>Les choses s'éloignent et les murmures résonnent dans les coins de mon esprit.</VAEI_SanityEffectWithoutInhumanized.stages.1.description>
  <VAEI_SanityEffectWithoutInhumanized.stages.1.label>santé mentale dégradée</VAEI_SanityEffectWithoutInhumanized.stages.1.label>
  <VAEI_SanityEffectWithoutInhumanized.stages.2.description>Mon emprise se desserre ; les ombres dansent et le monde tourne de manière incontrôlable.</VAEI_SanityEffectWithoutInhumanized.stages.2.description>
  <VAEI_SanityEffectWithoutInhumanized.stages.2.label>la raison s'effondre</VAEI_SanityEffectWithoutInhumanized.stages.2.label>
  <VAEI_SanityEffectWithoutInhumanized.stages.3.description>Je suis à la dérive dans le vide, détaché des ancres de la réalité et de la raison.</VAEI_SanityEffectWithoutInhumanized.stages.3.description>
  <VAEI_SanityEffectWithoutInhumanized.stages.3.label>santé mentale perdue</VAEI_SanityEffectWithoutInhumanized.stages.3.label>
  <VAEI_Suspicious.stages.0.label>suspect</VAEI_Suspicious.stages.0.label>
  <VAEI_VileSlanderMemory.stages.0.label>calomnie infâme</VAEI_VileSlanderMemory.stages.0.label>
  <VAEI_VileSlanderMood.stages.0.description>J'ai été accusé de quelque chose d'absolument ignoble ! Comment pouvaient-ils dire ça ?</VAEI_VileSlanderMood.stages.0.description>
  <VAEI_VileSlanderMood.stages.0.label>calomnie infâme</VAEI_VileSlanderMood.stages.0.label>
  <VAEI_VoidDrawings.stages.0.description>J'ai été témoin d'un dessin très étrange. J'ai l'impression que ça me parle.</VAEI_VoidDrawings.stages.0.description>
  <VAEI_VoidDrawings.stages.0.label>dessins des vides observés</VAEI_VoidDrawings.stages.0.label>
  <VAEI_VoidHarmed.stages.0.description>Je me suis fait du mal pour le vide. Je peux sentir la douce étreinte des ténèbres.</VAEI_VoidHarmed.stages.0.description>
  <VAEI_VoidHarmed.stages.0.label>vide blessé</VAEI_VoidHarmed.stages.0.label>
</LanguageData>
